{
  "$schema": "https://json-schema.org/draft/2020-12/schema",
  "title": "IssuerProfileDetails",
  "type": "object",
  "description": "Information about an Issuer as available on the server.",
  "properties": {
    "clientId": {
      "type": "string",
      "description": "Unique Issuer identifier from the Mastercard Developers."
    },
    "customerId": {
      "type": "string",
      "description": "Unique Issuer identifier assigned by Mastercard which remains the same across all Mastercard systems."
    },
    "supportedAccountRange": {
      "type": "string",
      "description": "Comma separated account range must be between 4 and 8 supported by an Issuer."
    },
    "status": {
      "type": "string",
      "description": "Status of an Issuer on the server. Possible values are Active and Suspended."
    },
    "email": {
      "type": "string",
      "description": "Issuers email address"
    },
    "countryCode": {
      "type": "string",
      "description": "DE 19 (Acquiring Institution Country Code) is the code of the country where the acquiring institution is located."
    },
    "privacyNoticeURL": {
      "type": "string",
      "description": "Privacy Notice URL."
    },
    "termsAndConditionURL": {
      "type": "string",
      "description": "Terms and conditions URL for the given user."
    },
    "optOutURL": {
      "type": "string",
      "description": "OPT out URL for the given user."
    }
  }
}